[
  {
    "id": 1,
    "name": "Guitar",
    "nameHi": "गिटार",
    "image": "images/instruments/guitar.jpg"
  },
  {
    "id": 2,
    "name": "Piano",
    "nameHi": "पियानो",
    "image": "images/instruments/piano.jpg"
  },
  {
    "id": 3,
    "name": "Drum",
    "nameHi": "ढोल",
    "image": "images/instruments/drum.jpg"
  },
  {
    "id": 4,
    "name": "Flute",
    "nameHi": "बांसुरी",
    "image": "images/instruments/flute.jpg"
  },
  {
    "id": 5,
    "name": "Violin",
    "nameHi": "वायलिन",
    "image": "images/instruments/violin.jpg"
  },
  {
    "id": 6,
    "name": "Trumpet",
    "nameHi": "तुरही",
    "image": "images/instruments/trumpet.jpg"
  },
  {
    "id": 7,
    "name": "Saxophone",
    "nameHi": "सैक्सोफोन",
    "image": "images/instruments/saxophone.jpg"
  },
  {
    "id": 8,
    "name": "Harmonium",
    "nameHi": "हारमोनियम",
    "image": "images/instruments/harmonium.jpg"
  },
  {
    "id": 9,
    "name": "Tabla",
    "nameHi": "तबला",
    "image": "images/instruments/tabla.jpg"
  },
  {
    "id": 10,
    "name": "Sitar",
    "nameHi": "सितार",
    "image": "images/instruments/sitar.jpg"
  },
  {
    "id": 11,
    "name": "Harp",
    "nameHi": "वीणा",
    "image": "images/instruments/harp.jpg"
  },
  {
    "id": 12,
    "name": "Accordion",
    "nameHi": "अकॉर्डियन",
    "image": "images/instruments/accordion.jpg"
  },
  {
    "id": 13,
    "name": "Banjo",
    "nameHi": "बैंजो",
    "image": "images/instruments/banjo.jpg"
  },
  {
    "id": 14,
    "name": "Clarinet",
    "nameHi": "शहनाई",
    "image": "images/instruments/clarinet.jpg"
  },
  {
    "id": 15,
    "name": "Cymbals",
    "nameHi": "झांझ",
    "image": "images/instruments/cymbals.jpg"
  },
  {
    "id": 16,
    "name": "Xylophone",
    "nameHi": "जाइलोफोन",
    "image": "images/instruments/xylophone.jpg"
  },
  {
    "id": 17,
    "name": "Tambourine",
    "nameHi": "डफली",
    "image": "images/instruments/tambourine.jpg"
  },
  {
    "id": 18,
    "name": "Mandolin",
    "nameHi": "मैंडोलिन",
    "image": "images/instruments/mandolin.jpg"
  },
  {
    "id": 19,
    "name": "Ukulele",
    "nameHi": "उकुलेले",
    "image": "images/instruments/ukulele.jpg"
  },
  {
    "id": 20,
    "name": "Trombone",
    "nameHi": "ट्रॉम्बोन",
    "image": "images/instruments/trombone.jpg"
  },
  {
    "id": 21,
    "name": "Cello",
    "nameHi": "सेलो",
    "image": "images/instruments/cello.jpg"
  },
  {
    "id": 22,
    "name": "Double Bass",
    "nameHi": "डबल बास",
    "image": "images/instruments/double_bass.jpg"
  },
  {
    "id": 23,
    "name": "Oboe",
    "nameHi": "ओबो",
    "image": "images/instruments/oboe.jpg"
  },
  {
    "id": 24,
    "name": "Bassoon",
    "nameHi": "बासून",
    "image": "images/instruments/bassoon.jpg"
  },
  {
    "id": 25,
    "name": "French Horn",
    "nameHi": "फ्रेंच हॉर्न",
    "image": "images/instruments/french_horn.jpg"
  },
  {
    "id": 26,
    "name": "Tuba",
    "nameHi": "टूबा",
    "image": "images/instruments/tuba.jpg"
  },
  {
    "id": 27,
    "name": "Piccolo",
    "nameHi": "पिकोलो",
    "image": "images/instruments/piccolo.jpg"
  },
  {
    "id": 28,
    "name": "Recorder",
    "nameHi": "रिकॉर्डर",
    "image": "images/instruments/recorder.jpg"
  },
  {
    "id": 29,
    "name": "Bagpipes",
    "nameHi": "बैगपाइप",
    "image": "images/instruments/bagpipes.jpg"
  },
  {
    "id": 30,
    "name": "Gong",
    "nameHi": "घंटा",
    "image": "images/instruments/gong.jpg"
  },
  {
    "id": 31,
    "name": "Triangle",
    "nameHi": "त्रिकोण",
    "image": "images/instruments/triangle.jpg"
  },
  {
    "id": 32,
    "name": "Maracas",
    "nameHi": "मराकस",
    "image": "images/instruments/maracas.jpg"
  },
  {
    "id": 33,
    "name": "Castanets",
    "nameHi": "कास्टानेट्स",
    "image": "images/instruments/castanets.jpg"
  },
  {
    "id": 34,
    "name": "Bongo Drums",
    "nameHi": "बोंगो ड्रम",
    "image": "images/instruments/bongo_drums.jpg"
  },
  {
    "id": 35,
    "name": "Conga",
    "nameHi": "कोंगा",
    "image": "images/instruments/conga.jpg"
  },
  {
    "id": 36,
    "name": "Djembe",
    "nameHi": "जेम्बे",
    "image": "images/instruments/djembe.jpg"
  },
  {
    "id": 37,
    "name": "Didgeridoo",
    "nameHi": "डिजेरिडू",
    "image": "images/instruments/didgeridoo.jpg"
  },
  {
    "id": 38,
    "name": "Kalimba",
    "nameHi": "कलिम्बा",
    "image": "images/instruments/kalimba.jpg"
  },
  {
    "id": 39,
    "name": "Synthesizer",
    "nameHi": "सिंथेसाइज़र",
    "image": "images/instruments/synthesizer.jpg"
  },
  {
    "id": 40,
    "name": "Electric Guitar",
    "nameHi": "इलेक्ट्रिक गिटार",
    "image": "images/instruments/electric_guitar.jpg"
  }
]
